killb/__init__.py
killb/account.py
killb/api_requests.py
killb/client.py
killb/exceptions.py
killb/quotations.py
killb/ramp.py
killb/savings.py
killb/user.py
killb/types/__init__.py
killb/types/account.py
killb/types/quotations.py
killb/types/ramps.py
killb/types/savings.py
killb/types/user.py
killb_sdk_python-1.0.4.dist-info/METADATA
killb_sdk_python-1.0.4.dist-info/WHEEL
killb_sdk_python-1.0.4.dist-info/top_level.txt
killb_sdk_python-1.0.4.dist-info/RECORD
