Metadata-Version: 2.1
Name: killb-sdk-python
Version: 1.0.4
Summary: SDK for KillB API V2
Home-page: https://github.com/Kill-B/sdk-python
Author: Kill-B
Classifier: Programming Language :: Python :: 3
Classifier: License :: OSI Approved :: MIT License
Classifier: Operating System :: OS Independent
Requires: requests
